jupyterpivot/__init__.py
jupyterpivot/_version.py
jupyterpivot/example.py
jupyterpivot/static/extension.js
jupyterpivot/static/index.js
jupyterpivot/static/index.js.map
jupyterpivot-0.1.0a0.data/data/etc/jupyter/nbconfig/notebook.d/jupyterpivot.json
jupyterpivot-0.1.0a0.data/data/share/jupyter/nbextensions/jupyterpivot/extension.js
jupyterpivot-0.1.0a0.data/data/share/jupyter/nbextensions/jupyterpivot/index.js
jupyterpivot-0.1.0a0.data/data/share/jupyter/nbextensions/jupyterpivot/index.js.map
jupyterpivot-0.1.0a0.dist-info/METADATA
jupyterpivot-0.1.0a0.dist-info/WHEEL
jupyterpivot-0.1.0a0.dist-info/top_level.txt
jupyterpivot-0.1.0a0.dist-info/RECORD
